{
  "canisters": {
    "calculator": {
      "main": "src/calculator/main.mo",
      "type": "motoko"
    },
    "homework_daily": {
      "main": "src/homework_daily/main.mo",
      "type": "motoko"
    },
    "student_wall": {
      "main": "src/student_wall/main.mo",
      "type": "motoko"
    },
    "motocoin": {
      "main": "src/motocoin/main.mo",
      "type": "motoko"
    }
  },
  "defaults": {
    "build": {
      "args": "",
      "packtool": ""
    }
  },
  "output_env_file": ".env",
  "version": 1
}
